Workbook

Sheet Executive_Summary
A1: Apple Inc. (AAPL) — DCF Valuation: Executive Summary
A2: Fiscal Year End: Late September | Valuation Date: Aug 12, 2026 | Method: 5-Year Unlevered FCFF DCF, Gordon Growth Terminal Value
A4: VALUATION SNAPSHOT
A5: Current Share Price | B5: =WACC_Calculation!B17 -> 301.58
A6: DCF-Implied Share Price (base case) | B6: =DCF_Valuation!B23 -> 131.72114
A7: Implied Upside / (Downside) | B7: =DCF_Valuation!B25 -> -0.56322986
A8: Enterprise Value ($mm) | B8: =DCF_Valuation!B18 -> 2021719.4
A9: Equity Value ($mm) | B9: =DCF_Valuation!B21 -> 1977759.4
A10: WACC | B10: =WACC_Calculation!B26 -> 0.094714664
A11: Terminal Growth Rate (g) | B11: =DCF_Valuation!B11 -> 0.025
A13: KEY HISTORICAL METRICS (FY2021 -> FY2025)
A14: Revenue ($mm) | B14: =Raw_Data!F6 -> 416161
A15: Revenue CAGR (FY21-FY25) | B15: =(Raw_Data!F6/Raw_Data!B6)^(1/4)-1 -> 0.032759916
A16: Gross Margin (FY2025) | B16: =Historical_Analysis!F7 -> 0.46905164
A17: Operating Margin (FY2025) | B17: =Historical_Analysis!F8 -> 0.319708
A18: ROIC (FY2025) | B18: =Historical_Analysis!F14 -> 0.95441772
A19: Cash Conversion Cycle (FY2025, days) | B19: =Historical_Analysis!F20 -> -71.068069
A20: Free Cash Flow (FY2025, $mm) | B20: =Raw_Data!F39 -> 98767
A22: KEY ASSUMPTIONS DRIVING THE VALUATION
A23: Revenue Growth, Yr 1 -> Yr 5 | B23: =Forecast_Model!C6 -> 0.08 | C23: -> | D23: =Forecast_Model!G6 -> 0.04
A24: Operating (EBIT) Margin, Yr 1 -> Yr 5 | B24: =Forecast_Model!C7 -> 0.325 | C24: -> | D24: =Forecast_Model!G7 -> 0.34
A25: Cost of Equity (Ke) | B25: =WACC_Calculation!C7 -> 0
A26: Cost of Debt, after-tax | B26: =WACC_Calculation!C14 -> 0
A28: INVESTMENT TAKEAWAYS
A29: - Apple has expanded operating margin from 29.8% (FY2021) to 32.0% (FY2025) as higher-margin Services revenue (now ~26% of sales) grows faster than hardware, while structurally negative working capital (CCC of roughly -70 days) means growth is self-funding rather than cash-consuming.
A30: - Under this model's base-case assumptions (8%->4% tapering revenue growth, 32.5%->34.0% EBIT margin, 9.5% WACC, 2.5% terminal growth), the DCF implies an intrinsic value below the current market price — the model's estimate of standalone unlevered FCFF value does not fully explain AAPL's market capitalization at the current share price.
A31: - This is a common pattern in DCFs of mega-cap 'compounders': a large share of market value reflects continued aggressive buybacks (~$97-100bn/year, shrinking the share count ~3-4%/year) compounding EPS per share beyond what an enterprise-level unlevered FCFF DCF captures, plus a scarcity/quality premium the market assigns to Apple's balance sheet and capital-return consistency.
A32: - The Sensitivity_Analysis tab shows the valuation is highly sensitive to the (WACC - g) spread: at the low end of the WACC range (7.5%) and high end of terminal growth (4.0%), the implied price rises to the low-$250s; at the high end of WACC (9.5%) and low end of growth (2.0%), it falls to the low-$120s. Users should treat the single-point 'implied share price' as the center of a wide, assumption-dependent range, not a precise target.
A33: - This model is for educational/illustrative purposes. It is not investment advice, and every hardcoded input should be re-verified against Apple's most recent 10-K/10-Q and current market data before being relied upon for any investment decision.
A35: WORKBOOK MAP
A36: Raw_Data | B36: FY2021-FY2025 income statement, balance sheet, and cash flow actuals (sourced from Apple's 10-K / StockAnalysis.com).
A37: Historical_Analysis | B37: Growth, margin, ROIC, and cash-conversion-cycle ratios calculated from Raw_Data.
A38: Forecast_Model | B38: 5-year unlevered FCFF forecast driven by editable assumption cells (yellow).
A39: WACC_Calculation | B39: Cost of equity (CAPM), cost of debt, capital structure weights, and WACC.
A40: DCF_Valuation | B40: PV of explicit FCFFs, Gordon Growth terminal value, and the bridge to implied share price.
A41: Sensitivity_Analysis | B41: Implied share price across a WACC (7.5%-9.5%) x terminal growth (2.0%-4.0%) grid.
A42: Executive_Summary | B42: This tab — a one-page roll-up of the valuation, key metrics, assumptions, and takeaways.

Sheet Raw_Data
A1: AAPL — Raw Financial Data (Historical, $ in millions)
A2: Apple Inc. | Fiscal year ends late September | Source: FY2025 Form 10-K (SEC EDGAR) and StockAnalysis.com (Fiscal.ai), retrieved Aug 12, 2026
A4: Line Item ($mm) | B4: FY2021 | C4: FY2022 | D4: FY2023 | E4: FY2024 | F4: FY2025
A5: INCOME STATEMENT
A6: Revenue, net | B6: 365817 | C6: 394328 | D6: 383285 | E6: 391035 | F6: 416161
A7: Cost of Goods Sold (COGS) | B7: 212981 | C7: 223546 | D7: 214137 | E7: 210352 | F7: 220960
A8: Gross Profit | B8: =B6-B7 -> 152836 | C8: =C6-C7 -> 170782 | D8: =D6-D7 -> 169148 | E8: =E6-E7 -> 180683 | F8: =F6-F7 -> 195201
A9: Research & Development | B9: 21914 | C9: 26251 | D9: 29915 | E9: 31370 | F9: 34550
A10: Selling, General & Admin. | B10: 21973 | C10: 25094 | D10: 24932 | E10: 26097 | F10: 27601
A11: Total Operating Expenses | B11: =B9+B10 -> 43887 | C11: =C9+C10 -> 51345 | D11: =D9+D10 -> 54847 | E11: =E9+E10 -> 57467 | F11: =F9+F10 -> 62151
A12: EBIT (Operating Income) | B12: =B8-B11 -> 108949 | C12: =C8-C11 -> 119437 | D12: =D8-D11 -> 114301 | E12: =E8-E11 -> 123216 | F12: =F8-F11 -> 133050
A13: Pretax Income | B13: 109197 | C13: 119087 | D13: 113729 | E13: 123481 | F13: 132673
A14: Income Tax Expense | B14: =B13-B16 -> 14517 | C14: =C13-C16 -> 19284 | D14: =D13-D16 -> 16734 | E14: =E13-E16 -> 29745 | F14: =F13-F16 -> 20663
A15: Effective Tax Rate | B15: =B14/B13 -> 0.13294321 | C15: =C14/C13 -> 0.16193203 | D15: =D14/D13 -> 0.14713925 | E15: =E14/E13 -> 0.24088726 | F15: =F14/F13 -> 0.15574382
A16: Net Income | B16: 94680 | C16: 99803 | D16: 96995 | E16: 93736 | F16: 112010
A17: Diluted EPS ($) | B17: 5.61 | C17: 6.11 | D17: 6.13 | E17: 6.08 | F17: 7.46
A18: Diluted Shares Outstanding (mm) | B18: =B16/B17 -> 16877.005 | C18: =C16/C17 -> 16334.37 | D18: =D16/D17 -> 15823.002 | E18: =E16/E17 -> 15417.105 | F18: =F16/F17 -> 15014.745
A20: BALANCE SHEET
A21: Cash & Cash Equivalents | B21: 34940 | C21: 23646 | D21: 29965 | E21: 29943 | F21: 35934
A22: Short-Term Investments | B22: 27699 | C22: 24658 | D22: 31590 | E22: 35228 | F22: 18763
A23: Cash & Investments (Total) | B23: =B21+B22 -> 62639 | C23: =C21+C22 -> 48304 | D23: =D21+D22 -> 61555 | E23: =E21+E22 -> 65171 | F23: =F21+F22 -> 54697
A24: Accounts Receivable, net | B24: 26278 | C24: 28184 | D24: 29508 | E24: 33410 | F24: 39777
A25: Inventory | B25: 6580 | C25: 4946 | D25: 6331 | E25: 7286 | F25: 5718
A26: Total Current Assets | B26: 134836 | C26: 135405 | D26: 143566 | E26: 152987 | F26: 147957
A27: Total Assets | B27: 351002 | C27: 352755 | D27: 352583 | E27: 364980 | F27: 359241
A28: Accounts Payable | B28: 54763 | C28: 64115 | D28: 62611 | E28: 68960 | F28: 69860
A29: Short-Term Debt (incl. current LTD) | B29: 15613 | C29: 21110 | D29: 15807 | E29: 20879 | F29: 20329
A30: Long-Term Debt | B30: 109106 | C30: 98959 | D30: 95281 | E30: 85750 | F30: 78328
A31: Total Debt | B31: =B29+B30 -> 124719 | C31: =C29+C30 -> 120069 | D31: =D29+D30 -> 111088 | E31: =E29+E30 -> 106629 | F31: =F29+F30 -> 98657
A32: Total Liabilities | B32: 287912 | C32: 302083 | D32: 290437 | E32: 308030 | F32: 285508
A33: Total Shareholders' Equity | B33: 63090 | C33: 50672 | D33: 62146 | E33: 56950 | F33: 73733
A35: CASH FLOW STATEMENT
A36: Cash Flow from Operations (OCF) | B36: 104038 | C36: 122151 | D36: 110543 | E36: 118254 | F36: 111482
A37: Depreciation & Amortization | B37: 11284 | C37: 11104 | D37: 11519 | E37: 11445 | F37: 11698
A38: Capital Expenditures (CapEx) | B38: 11085 | C38: 10708 | D38: 10959 | E38: 9447 | F38: 12715
A39: Free Cash Flow (OCF - CapEx) | B39: =B36-B38 -> 92953 | C39: =C36-C38 -> 111443 | D39: =D36-D38 -> 99584 | E39: =E36-E38 -> 108807 | F39: =F36-F38 -> 98767
A40: Dividends Paid | B40: 14467 | C40: 14841 | D40: 15025 | E40: 15234 | F40: 15421
A41: Share Repurchases (Buybacks) | B41: 92527 | C41: 95625 | D41: 82981 | E41: 100390 | F41: 96671
A43: Sources: Revenue/COGS/Opex/Pretax Income/Net Income/EPS/Balance Sheet/Cash Flow figures — Apple Inc. FY2025 Form 10-K (SEC EDGAR, CIK 0000320193) and StockAnalysis.com (data provider: Fiscal.ai), retrieved Aug 12, 2026: https://stockanalysis.com/stocks/aapl/financials/ . Gross Profit, Total OpEx, EBIT, Tax Expense, Effective Tax Rate, Diluted Shares, Cash & Investments, Total Debt, and Free Cash Flow are calculated in-sheet (black font). Blue cells are hardcoded historical inputs; update them each year from the new 10-K to refresh the entire model.

Sheet Historical_Analysis
A1: AAPL — Historical Ratio & Efficiency Analysis
A2: All figures calculated from Raw_Data tab (green = cross-sheet link, black = in-sheet formula)
A4: Metric | B4: FY2021 | C4: FY2022 | D4: FY2023 | E4: FY2024 | F4: FY2025
A5: GROWTH & PROFITABILITY
A6: Revenue Growth % | B6: n/a (base yr) | C6: =(Raw_Data!C6-Raw_Data!B6)/Raw_Data!B6 -> 0.077937876 | D6: =(Raw_Data!D6-Raw_Data!C6)/Raw_Data!C6 -> -0.028004605 | E6: =(Raw_Data!E6-Raw_Data!D6)/Raw_Data!D6 -> 0.020219941 | F6: =(Raw_Data!F6-Raw_Data!E6)/Raw_Data!E6 -> 0.064255118
A7: Gross Margin % | B7: =Raw_Data!B8/Raw_Data!B6 -> 0.4177936 | C7: =Raw_Data!C8/Raw_Data!C6 -> 0.43309631 | D7: =Raw_Data!D8/Raw_Data!D6 -> 0.4413113 | E7: =Raw_Data!E8/Raw_Data!E6 -> 0.4620635 | F7: =Raw_Data!F8/Raw_Data!F6 -> 0.46905164
A8: Operating Margin % (EBIT Margin) | B8: =Raw_Data!B12/Raw_Data!B6 -> 0.29782378 | C8: =Raw_Data!C12/Raw_Data!C6 -> 0.30288744 | D8: =Raw_Data!D12/Raw_Data!D6 -> 0.29821412 | E8: =Raw_Data!E12/Raw_Data!E6 -> 0.31510223 | F8: =Raw_Data!F12/Raw_Data!F6 -> 0.319708
A9: Net Margin % | B9: =Raw_Data!B16/Raw_Data!B6 -> 0.25881793 | C9: =Raw_Data!C16/Raw_Data!C6 -> 0.25309641 | D9: =Raw_Data!D16/Raw_Data!D6 -> 0.25306234 | E9: =Raw_Data!E16/Raw_Data!E6 -> 0.23971256 | F9: =Raw_Data!F16/Raw_Data!F6 -> 0.26915064
A11: RETURNS: ROIC
A12: NOPAT = EBIT x (1 - Tax Rate) | B12: =Raw_Data!B12*(1-Raw_Data!B15) -> 94464.97 | C12: =Raw_Data!C12*(1-Raw_Data!C15) -> 100096.32 | D12: =Raw_Data!D12*(1-Raw_Data!D15) -> 97482.836 | E12: =Raw_Data!E12*(1-Raw_Data!E15) -> 93534.835 | F12: =Raw_Data!F12*(1-Raw_Data!F15) -> 112328.28
A13: Invested Capital = Total Debt + Equity - Cash | B13: =Raw_Data!B31+Raw_Data!B33-Raw_Data!B23 -> 125170 | C13: =Raw_Data!C31+Raw_Data!C33-Raw_Data!C23 -> 122437 | D13: =Raw_Data!D31+Raw_Data!D33-Raw_Data!D23 -> 111679 | E13: =Raw_Data!E31+Raw_Data!E33-Raw_Data!E23 -> 98408 | F13: =Raw_Data!F31+Raw_Data!F33-Raw_Data!F23 -> 117693
A14: ROIC = NOPAT / Invested Capital | B14: =B12/B13 -> 0.75469338 | C14: =C12/C13 -> 0.81753329 | D14: =D12/D13 -> 0.87288422 | E14: =E12/E13 -> 0.95047999 | F14: =F12/F13 -> 0.95441772 | H14: Apple's invested capital is often small or negative (net cash position + buybacks reducing equity), which can make ROIC very large or not economically meaningful — read alongside operating margin trends, not in isolation.
A16: CASH CONVERSION CYCLE (WORKING CAPITAL EFFICIENCY)
A17: DSO = Accounts Receivable / Revenue x 365 | B17: =Raw_Data!B24/Raw_Data!B6*365 -> 26.219312 | C17: =Raw_Data!C24/Raw_Data!C6*365 -> 26.087825 | D17: =Raw_Data!D24/Raw_Data!D6*365 -> 28.100291 | E17: =Raw_Data!E24/Raw_Data!E6*365 -> 31.185572 | F17: =Raw_Data!F24/Raw_Data!F6*365 -> 34.886991
A18: DIO = Inventory / COGS x 365 | B18: =Raw_Data!B25/Raw_Data!B7*365 -> 11.276593 | C18: =Raw_Data!C25/Raw_Data!C7*365 -> 8.0756981 | D18: =Raw_Data!D25/Raw_Data!D7*365 -> 10.791292 | E18: =Raw_Data!E25/Raw_Data!E7*365 -> 12.642571 | F18: =Raw_Data!F25/Raw_Data!F7*365 -> 9.4454652
A19: DPO = Accounts Payable / COGS x 365 | B19: =Raw_Data!B28/Raw_Data!B7*365 -> 93.851071 | C19: =Raw_Data!C28/Raw_Data!C7*365 -> 104.68528 | D19: =Raw_Data!D28/Raw_Data!D7*365 -> 106.72147 | E19: =Raw_Data!E28/Raw_Data!E7*365 -> 119.65848 | F19: =Raw_Data!F28/Raw_Data!F7*365 -> 115.40052
A20: Cash Conversion Cycle (CCC) = DSO + DIO - DPO | B20: =B17+B18-B19 -> -56.355167 | C20: =C17+C18-C19 -> -70.521754 | D20: =D17+D18-D19 -> -67.829885 | E20: =E17+E18-E19 -> -75.830335 | F20: =F17+F18-F19 -> -71.068069 | H20: Apple runs a structurally negative CCC: suppliers (via Accounts Payable / DPO) effectively finance its inventory and receivables, so cash is collected before it is paid out — a hallmark of Apple's supply-chain bargaining power.
A22: LEVERAGE & LIQUIDITY
A23: Net Debt (Cash) = Total Debt - Cash & Investments | B23: =Raw_Data!B31-Raw_Data!B23 -> 62080 | C23: =Raw_Data!C31-Raw_Data!C23 -> 71765 | D23: =Raw_Data!D31-Raw_Data!D23 -> 49533 | E23: =Raw_Data!E31-Raw_Data!E23 -> 41458 | F23: =Raw_Data!F31-Raw_Data!F23 -> 43960
A24: Total Debt / Equity | B24: =Raw_Data!B31/Raw_Data!B33 -> 1.9768426 | C24: =Raw_Data!C31/Raw_Data!C33 -> 2.3695335 | D24: =Raw_Data!D31/Raw_Data!D33 -> 1.7875326 | E24: =Raw_Data!E31/Raw_Data!E33 -> 1.8723266 | F24: =Raw_Data!F31/Raw_Data!F33 -> 1.3380305
A26: All ratios recalculate automatically from Raw_Data. To refresh with a new fiscal year: (1) add the new year's actuals to Raw_Data, (2) extend the column ranges on this tab and the Forecast_Model tab, (3) re-run the workbook's recalculation.

Sheet Forecast_Model
A1: AAPL — 5-Year Unlevered Free Cash Flow (FCFF) Forecast
A2: Yellow = key assumption inputs (edit these to run scenarios). FCFF = EBIT x (1 - Tax Rate) + D&A - CapEx - Change in NWC
A4: Driver / Line Item | B4: FY2025A | C4: Year 1 (FY2026E) | D4: Year 2 (FY2027E) | E4: Year 3 (FY2028E) | F4: Year 4 (FY2029E) | G4: Year 5 (FY2030E)
A5: OPERATING ASSUMPTIONS (edit yellow cells to run scenarios)
A6: Revenue Growth % | C6: 0.08 | D6: 0.07 | E6: 0.06 | F6: 0.05 | G6: 0.04
A7: Operating (EBIT) Margin % | C7: 0.325 | D7: 0.33 | E7: 0.333 | F7: 0.336 | G7: 0.34
A8: Cash Tax Rate % | C8: 0.16 | D8: 0.16 | E8: 0.16 | F8: 0.16 | G8: 0.16
A9: D&A % of Revenue | C9: 0.028 | D9: 0.028 | E9: 0.028 | F9: 0.028 | G9: 0.028
A10: CapEx % of Revenue | C10: 0.031 | D10: 0.031 | E10: 0.031 | F10: 0.031 | G10: 0.031
A11: NWC % of Revenue (Chg. in NWC = % x Chg. in Revenue) | C11: -0.058 | D11: -0.058 | E11: -0.058 | F11: -0.058 | G11: -0.058 | H11: Assumptions (blue/yellow): revenue growth tapering 8%→4% reflects Services mix-shift plus an AI-driven iPhone upgrade cycle, moderating toward GDP+ long-run growth; EBIT margin expanding 32.5%→34.0% continues the FY2021-FY2025 trend (29.8%→32.0%) as Services (higher-margin) grows faster than hardware; cash tax rate of 16.0% approximates AAPL's FY2021-FY2023/FY2025 average effective rate (13-16%), excluding the one-off FY2024 EU State Aid charge; D&A and CapEx held near their FY2025 ratios of 2.8% and 3.1% of revenue; NWC ratio of -5.8% of revenue matches FY2025 (Apple has structurally negative working capital, so revenue growth is a modest source of cash, not a use). These are illustrative, editable inputs — not analyst consensus forecasts.
A13: FCFF BUILD
A14: Revenue | B14: =Raw_Data!F6 -> 416161 | C14: =B14*(1+C6) -> 449453.88 | D14: =C14*(1+D6) -> 480915.65 | E14: =D14*(1+E6) -> 509770.59 | F14: =E14*(1+F6) -> 535259.12 | G14: =F14*(1+G6) -> 556669.49
A15: EBIT | C15: =C14*C7 -> 146072.51 | D15: =D14*D7 -> 158702.17 | E15: =E14*E7 -> 169753.61 | F15: =F14*F7 -> 179847.06 | G15: =G14*G7 -> 189267.62
A16: Less: Tax on EBIT | C16: =-C15*C8 -> -23371.602 | D16: =-D15*D8 -> -25392.346 | E16: =-E15*E8 -> -27160.577 | F16: =-F15*F8 -> -28775.53 | G16: =-G15*G8 -> -30282.82
A17: NOPAT = EBIT x (1 - Tax Rate) | C17: =C15+C16 -> 122700.91 | D17: =D15+D16 -> 133309.82 | E17: =E15+E16 -> 142593.03 | F17: =F15+F16 -> 151071.53 | G17: =G15+G16 -> 158984.8
A18: Plus: D&A | C18: =C14*C9 -> 12584.709 | D18: =D14*D9 -> 13465.638 | E18: =E14*E9 -> 14273.577 | F18: =F14*F9 -> 14987.255 | G18: =G14*G9 -> 15586.746
A19: Less: CapEx | C19: =-C14*C10 -> -13933.07 | D19: =-D14*D10 -> -14908.385 | E19: =-E14*E10 -> -15802.888 | F19: =-F14*F10 -> -16593.033 | G19: =-G14*G10 -> -17256.754
A20: Less: Change in NWC | C20: =-((C14-B14)*C11) -> 1930.987 | D20: =-((D14-C14)*D11) -> 1824.7828 | E20: =-((E14-D14)*E11) -> 1673.5865 | F20: =-((F14-E14)*F11) -> 1478.3347 | G20: =-((G14-F14)*G11) -> 1241.8012
A21: Unlevered FCFF | B21: =Raw_Data!F39 -> 98767 | C21: =C17+C18+C19+C20 -> 123283.53 | D21: =D17+D18+D19+D20 -> 133691.85 | E21: =E17+E18+E19+E20 -> 142737.3 | F21: =F17+F18+F19+F20 -> 150944.09 | G21: =G17+G18+G19+G20 -> 158556.6
A22: FCFF Growth % | C22: =C21/B21-1 -> 0.24822597 | D22: =D21/C21-1 -> 0.084425871 | E22: =E21/D21-1 -> 0.067658946 | F22: =F21/E21-1 -> 0.057495741 | G22: =G21/F21-1 -> 0.050432621
A24: FCFF Year 1 base (FY2025 Revenue) links to Raw_Data (green). Every driver row is a labeled, editable assumption — change any yellow cell and the entire FCFF build, the DCF_Valuation tab, and the Sensitivity_Analysis tab recalculate automatically.

Sheet WACC_Calculation
A1: AAPL — Weighted Average Cost of Capital (WACC)
A3: COST OF EQUITY (CAPM)
A4: Risk-Free Rate (Rf) — 10Y U.S. Treasury yield | B4: 0.0425 | D4: Rf, Beta and ERP are the model's key market-risk assumptions (blue/yellow, editable). Rf approximates the 10Y U.S. Treasury yield; Beta of 1.08 and ERP of 5.0% are standard reference-level inputs for a large-cap U.S. tech name. Update these periodically from a market-data source (e.g., Treasury.gov for Rf; Bloomberg/Damodaran for beta and ERP).
A5: Beta (β) — levered, vs. S&P 500 | B5: 1.08
A6: Equity Risk Premium (ERP) | B6: 0.05
A7: Cost of Equity: Ke = Rf + β x ERP | B7: =B4+B5*B6 -> 0.0965
A9: COST OF DEBT
A10: Estimated Annual Interest Expense on Debt ($mm) | B10: 1500 | D10: Apple does not disclose a single 'interest expense' line on the income statement (it nets interest income/expense within Other Income/(Expense)). $1,500mm is a documented estimate consistent with public disclosures of Apple's outstanding term debt and coupon schedule (Apple 10-K Note on Debt; quarterly interest-expense-on-debt trackers such as Trading Economics show ~$300-450mm/quarter through FY2025). Adjust this blue cell if you have a more precise figure.
A11: Total Debt (FY2025, from Raw_Data) | B11: =Raw_Data!F31 -> 98657
A12: Pretax Cost of Debt: Kd = Interest Expense / Total Debt | B12: =B10/B11 -> 0.015204192
A13: Marginal Tax Rate (t), linked to Forecast_Model | B13: =Forecast_Model!C8 -> 0.16
A14: After-Tax Cost of Debt: Kd x (1 - t) | B14: =B12*(1-B13) -> 0.012771522
A16: CAPITAL STRUCTURE (MARKET VALUES)
A17: Current Share Price ($) | B17: 301.58 | D17: Share price is a point-in-time market input — StockAnalysis.com quote, Aug 12, 2026 (intraday). Market value of debt is approximated by book value of total debt, a standard simplification since Apple's bonds trade close to par given its AA+ credit rating.
A18: Diluted Shares Outstanding (mm), FY2025 | B18: =Raw_Data!F18 -> 15014.745
A19: Market Value of Equity (E) = Price x Diluted Shares | B19: =B17*B18 -> 4528146.9
A20: Market Value of Debt (D) ≈ Book Value of Total Debt | B20: =B11 -> 98657
A21: Total Capital (V) = E + D | B21: =B19+B20 -> 4626803.9
A22: Weight of Equity (E / V) | B22: =B19/B21 -> 0.97867707
A23: Weight of Debt (D / V) | B23: =B20/B21 -> 0.021322927
A25: WACC
A26: WACC = (E/V x Ke) + (D/V x Kd x (1 - t)) | B26: =(B22*B7)+(B23*B14) -> 0.094714664
A28: Because Apple carries very little leverage relative to its market capitalization (D/V is typically under 3%), WACC sits close to the pure cost of equity. This is a standard, expected result for a mega-cap, investment-grade technology company.

Sheet DCF_Valuation
A1: AAPL — DCF Valuation Bridge: Enterprise Value to Implied Share Price
A3: Year | C3: Year 1 | D3: Year 2 | E3: Year 3 | F3: Year 4 | G3: Year 5
A4: Unlevered FCFF (from Forecast_Model) | C4: =Forecast_Model!C21 -> 123283.53 | D4: =Forecast_Model!D21 -> 133691.85 | E4: =Forecast_Model!E21 -> 142737.3 | F4: =Forecast_Model!F21 -> 150944.09 | G4: =Forecast_Model!G21 -> 158556.6
A5: Discount Period (t) | C5: 1 | D5: 2 | E5: 3 | F5: 4 | G5: 5
A6: Discount Factor = 1 / (1 + WACC)^t | C6: =1/(1+WACC_Calculation!$B$26)^C5 -> 0.91348004 | D6: =1/(1+WACC_Calculation!$B$26)^D5 -> 0.83444579 | E6: =1/(1+WACC_Calculation!$B$26)^E5 -> 0.76224958 | F6: =1/(1+WACC_Calculation!$B$26)^F5 -> 0.69629978 | G6: =1/(1+WACC_Calculation!$B$26)^G5 -> 0.63605595
A7: PV of FCFF | C7: =C4*C6 -> 112617.05 | D7: =D4*D6 -> 111558.61 | E7: =E4*E6 -> 108801.45 | F7: =F4*F6 -> 105102.34 | G7: =G4*G6 -> 100850.87
A9: EXPLICIT PERIOD & TERMINAL VALUE
A10: Sum of PV of Explicit FCFFs (Years 1-5) | B10: =SUM(C7:G7) -> 538930.31
A11: Terminal Growth Rate (g) | B11: 0.025 | D11: Terminal growth rate of 2.5% sits mid-range of the Sensitivity_Analysis grid (2.0%-4.0%) and approximates long-run nominal GDP growth — a standard, conservative anchor for a Gordon Growth terminal value so the terminal period doesn't assume perpetual above-GDP growth.
A12: WACC (from WACC_Calculation) | B12: =WACC_Calculation!B26 -> 0.094714664
A13: Terminal Value = FCFF5 x (1+g) / (WACC - g) | B13: =(G4*(1+B11))/(B12-B11) -> 2331224.2
A14: PV of Terminal Value = TV / (1 + WACC)^5 | B14: =B13/(1+B12)^5 -> 1482789
A17: ENTERPRISE VALUE TO SHARE PRICE BRIDGE
A18: Enterprise Value (EV) = PV of Explicit FCFs + PV of Terminal Value | B18: =B10+B14 -> 2021719.4
A19: Plus: Cash & Investments (FY2025) | B19: =Raw_Data!F23 -> 54697
A20: Less: Total Debt (FY2025) | B20: =-Raw_Data!F31 -> -98657
A21: Equity Value = EV + Cash - Total Debt | B21: =B18+B19+B20 -> 1977759.4
A22: Diluted Shares Outstanding (mm) | B22: =Raw_Data!F18 -> 15014.745
A23: Implied Share Price = Equity Value / Diluted Shares | B23: =B21/B22 -> 131.72114
A24: Current Share Price (from WACC_Calculation) | B24: =WACC_Calculation!B17 -> 301.58
A25: Implied Upside / (Downside) vs. Current Price | B25: =B23/B24-1 -> -0.56322986
A27: This DCF bridge is fully dynamic: it flows from Forecast_Model's FCFF (green links), discounts at the WACC computed on WACC_Calculation, and nets FY2025 cash/debt and diluted shares from Raw_Data. Change any assumption anywhere in the workbook and every number here — including the implied share price — recalculates.

Sheet Sensitivity_Analysis
A1: AAPL — Sensitivity Analysis: Implied Share Price by WACC and Terminal Growth
A2: Note: this grid uses live formulas (not Excel's What-If 'Data Table' feature, which requires manual recalculation and isn't portable across spreadsheet engines) — every cell independently rebuilds the full DCF bridge for its own WACC/g pair, so it recalculates automatically like the rest of the model.
A4: Implied Share Price ($)
A5: WACC \ Terminal Growth (g) -> | C5: 0.02 | D5: 0.025 | E5: 0.03 | F5: 0.035 | G5: 0.04
A6: 0.075 | C6: =((INDEX(Forecast_Model!$C$21:$G$21,1)/(1+$A6)^1+INDEX(Forecast_Model!$C$21:$G$21,2)/(1+$A6)^2+INDEX(Forecast_Model!$C$21:$G$21,3)/(1+$A6)^3+INDEX(Forecast_Model!$C$21:$G$21,4)/(1+$A6)^4+INDEX(Forecast_Model!$C$21:$G$21,5)/(1+$A6)^5+((INDEX(Forecast_Model!$C$21:$G$21,5)*(1+C$5))/($A6-C$5))/(1+$A6)^5)+Raw_Data!$F$23-Raw_Data!$F$31)/Raw_Data!$F$18 -> 171.36573 | D6: =((INDEX(Forecast_Model!$C$21:$G$21,1)/(1+$A6)^1+INDEX(Forecast_Model!$C$21:$G$21,2)/(1+$A6)^2+INDEX(Forecast_Model!$C$21:$G$21,3)/(1+$A6)^3+INDEX(Forecast_Model!$C$21:$G$21,4)/(1+$A6)^4+INDEX(Forecast_Model!$C$21:$G$21,5)/(1+$A6)^5+((INDEX(Forecast_Model!$C$21:$G$21,5)*(1+D$5))/($A6-D$5))/(1+$A6)^5)+Raw_Data!$F$23-Raw_Data!$F$31)/Raw_Data!$F$18 -> 185.74278 | E6: =((INDEX(Forecast_Model!$C$21:$G$21,1)/(1+$A6)^1+INDEX(Forecast_Model!$C$21:$G$21,2)/(1+$A6)^2+INDEX(Forecast_Model!$C$21:$G$21,3)/(1+$A6)^3+INDEX(Forecast_Model!$C$21:$G$21,4)/(1+$A6)^4+INDEX(Forecast_Model!$C$21:$G$21,5)/(1+$A6)^5+((INDEX(Forecast_Model!$C$21:$G$21,5)*(1+E$5))/($A6-E$5))/(1+$A6)^5)+Raw_Data!$F$23-Raw_Data!$F$31)/Raw_Data!$F$18 -> 203.31473 | F6: =((INDEX(Forecast_Model!$C$21:$G$21,1)/(1+$A6)^1+INDEX(Forecast_Model!$C$21:$G$21,2)/(1+$A6)^2+INDEX(Forecast_Model!$C$21:$G$21,3)/(1+$A6)^3+INDEX(Forecast_Model!$C$21:$G$21,4)/(1+$A6)^4+INDEX(Forecast_Model!$C$21:$G$21,5)/(1+$A6)^5+((INDEX(Forecast_Model!$C$21:$G$21,5)*(1+F$5))/($A6-F$5))/(1+$A6)^5)+Raw_Data!$F$23-Raw_Data!$F$31)/Raw_Data!$F$18 -> 225.27967 | G6: =((INDEX(Forecast_Model!$C$21:$G$21,1)/(1+$A6)^1+INDEX(Forecast_Model!$C$21:$G$21,2)/(1+$A6)^2+INDEX(Forecast_Model!$C$21:$G$21,3)/(1+$A6)^3+INDEX(Forecast_Model!$C$21:$G$21,4)/(1+$A6)^4+INDEX(Forecast_Model!$C$21:$G$21,5)/(1+$A6)^5+((INDEX(Forecast_Model!$C$21:$G$21,5)*(1+G$5))/($A6-G$5))/(1+$A6)^5)+Raw_Data!$F$23-Raw_Data!$F$31)/Raw_Data!$F$18 -> 253.5203
A7: 0.08 | C7: =((INDEX(Forecast_Model!$C$21:$G$21,1)/(1+$A7)^1+INDEX(Forecast_Model!$C$21:$G$21,2)/(1+$A7)^2+INDEX(Forecast_Model!$C$21:$G$21,3)/(1+$A7)^3+INDEX(Forecast_Model!$C$21:$G$21,4)/(1+$A7)^4+INDEX(Forecast_Model!$C$21:$G$21,5)/(1+$A7)^5+((INDEX(Forecast_Model!$C$21:$G$21,5)*(1+C$5))/($A7-C$5))/(1+$A7)^5)+Raw_Data!$F$23-Raw_Data!$F$31)/Raw_Data!$F$18 -> 156.61043 | D7: =((INDEX(Forecast_Model!$C$21:$G$21,1)/(1+$A7)^1+INDEX(Forecast_Model!$C$21:$G$21,2)/(1+$A7)^2+INDEX(Forecast_Model!$C$21:$G$21,3)/(1+$A7)^3+INDEX(Forecast_Model!$C$21:$G$21,4)/(1+$A7)^4+INDEX(Forecast_Model!$C$21:$G$21,5)/(1+$A7)^5+((INDEX(Forecast_Model!$C$21:$G$21,5)*(1+D$5))/($A7-D$5))/(1+$A7)^5)+Raw_Data!$F$23-Raw_Data!$F$31)/Raw_Data!$F$18 -> 168.37097 | E7: =((INDEX(Forecast_Model!$C$21:$G$21,1)/(1+$A7)^1+INDEX(Forecast_Model!$C$21:$G$21,2)/(1+$A7)^2+INDEX(Forecast_Model!$C$21:$G$21,3)/(1+$A7)^3+INDEX(Forecast_Model!$C$21:$G$21,4)/(1+$A7)^4+INDEX(Forecast_Model!$C$21:$G$21,5)/(1+$A7)^5+((INDEX(Forecast_Model!$C$21:$G$21,5)*(1+E$5))/($A7-E$5))/(1+$A7)^5)+Raw_Data!$F$23-Raw_Data!$F$31)/Raw_Data!$F$18 -> 182.48363 | F7: =((INDEX(Forecast_Model!$C$21:$G$21,1)/(1+$A7)^1+INDEX(Forecast_Model!$C$21:$G$21,2)/(1+$A7)^2+INDEX(Forecast_Model!$C$21:$G$21,3)/(1+$A7)^3+INDEX(Forecast_Model!$C$21:$G$21,4)/(1+$A7)^4+INDEX(Forecast_Model!$C$21:$G$21,5)/(1+$A7)^5+((INDEX(Forecast_Model!$C$21:$G$21,5)*(1+F$5))/($A7-F$5))/(1+$A7)^5)+Raw_Data!$F$23-Raw_Data!$F$31)/Raw_Data!$F$18 -> 199.73242 | G7: =((INDEX(Forecast_Model!$C$21:$G$21,1)/(1+$A7)^1+INDEX(Forecast_Model!$C$21:$G$21,2)/(1+$A7)^2+INDEX(Forecast_Model!$C$21:$G$21,3)/(1+$A7)^3+INDEX(Forecast_Model!$C$21:$G$21,4)/(1+$A7)^4+INDEX(Forecast_Model!$C$21:$G$21,5)/(1+$A7)^5+((INDEX(Forecast_Model!$C$21:$G$21,5)*(1+G$5))/($A7-G$5))/(1+$A7)^5)+Raw_Data!$F$23-Raw_Data!$F$31)/Raw_Data!$F$18 -> 221.29342
A8: 0.085 | C8: =((INDEX(Forecast_Model!$C$21:$G$21,1)/(1+$A8)^1+INDEX(Forecast_Model!$C$21:$G$21,2)/(1+$A8)^2+INDEX(Forecast_Model!$C$21:$G$21,3)/(1+$A8)^3+INDEX(Forecast_Model!$C$21:$G$21,4)/(1+$A8)^4+INDEX(Forecast_Model!$C$21:$G$21,5)/(1+$A8)^5+((INDEX(Forecast_Model!$C$21:$G$21,5)*(1+C$5))/($A8-C$5))/(1+$A8)^5)+Raw_Data!$F$23-Raw_Data!$F$31)/Raw_Data!$F$18 -> 144.12883 | D8: =((INDEX(Forecast_Model!$C$21:$G$21,1)/(1+$A8)^1+INDEX(Forecast_Model!$C$21:$G$21,2)/(1+$A8)^2+INDEX(Forecast_Model!$C$21:$G$21,3)/(1+$A8)^3+INDEX(Forecast_Model!$C$21:$G$21,4)/(1+$A8)^4+INDEX(Forecast_Model!$C$21:$G$21,5)/(1+$A8)^5+((INDEX(Forecast_Model!$C$21:$G$21,5)*(1+D$5))/($A8-D$5))/(1+$A8)^5)+Raw_Data!$F$23-Raw_Data!$F$31)/Raw_Data!$F$18 -> 153.89789 | E8: =((INDEX(Forecast_Model!$C$21:$G$21,1)/(1+$A8)^1+INDEX(Forecast_Model!$C$21:$G$21,2)/(1+$A8)^2+INDEX(Forecast_Model!$C$21:$G$21,3)/(1+$A8)^3+INDEX(Forecast_Model!$C$21:$G$21,4)/(1+$A8)^4+INDEX(Forecast_Model!$C$21:$G$21,5)/(1+$A8)^5+((INDEX(Forecast_Model!$C$21:$G$21,5)*(1+E$5))/($A8-E$5))/(1+$A8)^5)+Raw_Data!$F$23-Raw_Data!$F$31)/Raw_Data!$F$18 -> 165.44314 | F8: =((INDEX(Forecast_Model!$C$21:$G$21,1)/(1+$A8)^1+INDEX(Forecast_Model!$C$21:$G$21,2)/(1+$A8)^2+INDEX(Forecast_Model!$C$21:$G$21,3)/(1+$A8)^3+INDEX(Forecast_Model!$C$21:$G$21,4)/(1+$A8)^4+INDEX(Forecast_Model!$C$21:$G$21,5)/(1+$A8)^5+((INDEX(Forecast_Model!$C$21:$G$21,5)*(1+F$5))/($A8-F$5))/(1+$A8)^5)+Raw_Data!$F$23-Raw_Data!$F$31)/Raw_Data!$F$18 -> 179.29744 | G8: =((INDEX(Forecast_Model!$C$21:$G$21,1)/(1+$A8)^1+INDEX(Forecast_Model!$C$21:$G$21,2)/(1+$A8)^2+INDEX(Forecast_Model!$C$21:$G$21,3)/(1+$A8)^3+INDEX(Forecast_Model!$C$21:$G$21,4)/(1+$A8)^4+INDEX(Forecast_Model!$C$21:$G$21,5)/(1+$A8)^5+((INDEX(Forecast_Model!$C$21:$G$21,5)*(1+G$5))/($A8-G$5))/(1+$A8)^5)+Raw_Data!$F$23-Raw_Data!$F$31)/Raw_Data!$F$18 -> 196.23048
A9: 0.09 | C9: =((INDEX(Forecast_Model!$C$21:$G$21,1)/(1+$A9)^1+INDEX(Forecast_Model!$C$21:$G$21,2)/(1+$A9)^2+INDEX(Forecast_Model!$C$21:$G$21,3)/(1+$A9)^3+INDEX(Forecast_Model!$C$21:$G$21,4)/(1+$A9)^4+INDEX(Forecast_Model!$C$21:$G$21,5)/(1+$A9)^5+((INDEX(Forecast_Model!$C$21:$G$21,5)*(1+C$5))/($A9-C$5))/(1+$A9)^5)+Raw_Data!$F$23-Raw_Data!$F$31)/Raw_Data!$F$18 -> 133.43362 | D9: =((INDEX(Forecast_Model!$C$21:$G$21,1)/(1+$A9)^1+INDEX(Forecast_Model!$C$21:$G$21,2)/(1+$A9)^2+INDEX(Forecast_Model!$C$21:$G$21,3)/(1+$A9)^3+INDEX(Forecast_Model!$C$21:$G$21,4)/(1+$A9)^4+INDEX(Forecast_Model!$C$21:$G$21,5)/(1+$A9)^5+((INDEX(Forecast_Model!$C$21:$G$21,5)*(1+D$5))/($A9-D$5))/(1+$A9)^5)+Raw_Data!$F$23-Raw_Data!$F$31)/Raw_Data!$F$18 -> 141.65451 | E9: =((INDEX(Forecast_Model!$C$21:$G$21,1)/(1+$A9)^1+INDEX(Forecast_Model!$C$21:$G$21,2)/(1+$A9)^2+INDEX(Forecast_Model!$C$21:$G$21,3)/(1+$A9)^3+INDEX(Forecast_Model!$C$21:$G$21,4)/(1+$A9)^4+INDEX(Forecast_Model!$C$21:$G$21,5)/(1+$A9)^5+((INDEX(Forecast_Model!$C$21:$G$21,5)*(1+E$5))/($A9-E$5))/(1+$A9)^5)+Raw_Data!$F$23-Raw_Data!$F$31)/Raw_Data!$F$18 -> 151.24555 | F9: =((INDEX(Forecast_Model!$C$21:$G$21,1)/(1+$A9)^1+INDEX(Forecast_Model!$C$21:$G$21,2)/(1+$A9)^2+INDEX(Forecast_Model!$C$21:$G$21,3)/(1+$A9)^3+INDEX(Forecast_Model!$C$21:$G$21,4)/(1+$A9)^4+INDEX(Forecast_Model!$C$21:$G$21,5)/(1+$A9)^5+((INDEX(Forecast_Model!$C$21:$G$21,5)*(1+F$5))/($A9-F$5))/(1+$A9)^5)+Raw_Data!$F$23-Raw_Data!$F$31)/Raw_Data!$F$18 -> 162.58042 | G9: =((INDEX(Forecast_Model!$C$21:$G$21,1)/(1+$A9)^1+INDEX(Forecast_Model!$C$21:$G$21,2)/(1+$A9)^2+INDEX(Forecast_Model!$C$21:$G$21,3)/(1+$A9)^3+INDEX(Forecast_Model!$C$21:$G$21,4)/(1+$A9)^4+INDEX(Forecast_Model!$C$21:$G$21,5)/(1+$A9)^5+((INDEX(Forecast_Model!$C$21:$G$21,5)*(1+G$5))/($A9-G$5))/(1+$A9)^5)+Raw_Data!$F$23-Raw_Data!$F$31)/Raw_Data!$F$18 -> 176.18226
A10: 0.095 | C10: =((INDEX(Forecast_Model!$C$21:$G$21,1)/(1+$A10)^1+INDEX(Forecast_Model!$C$21:$G$21,2)/(1+$A10)^2+INDEX(Forecast_Model!$C$21:$G$21,3)/(1+$A10)^3+INDEX(Forecast_Model!$C$21:$G$21,4)/(1+$A10)^4+INDEX(Forecast_Model!$C$21:$G$21,5)/(1+$A10)^5+((INDEX(Forecast_Model!$C$21:$G$21,5)*(1+C$5))/($A10-C$5))/(1+$A10)^5)+Raw_Data!$F$23-Raw_Data!$F$31)/Raw_Data!$F$18 -> 124.16745 | D10: =((INDEX(Forecast_Model!$C$21:$G$21,1)/(1+$A10)^1+INDEX(Forecast_Model!$C$21:$G$21,2)/(1+$A10)^2+INDEX(Forecast_Model!$C$21:$G$21,3)/(1+$A10)^3+INDEX(Forecast_Model!$C$21:$G$21,4)/(1+$A10)^4+INDEX(Forecast_Model!$C$21:$G$21,5)/(1+$A10)^5+((INDEX(Forecast_Model!$C$21:$G$21,5)*(1+D$5))/($A10-D$5))/(1+$A10)^5)+Raw_Data!$F$23-Raw_Data!$F$31)/Raw_Data!$F$18 -> 131.16298 | E10: =((INDEX(Forecast_Model!$C$21:$G$21,1)/(1+$A10)^1+INDEX(Forecast_Model!$C$21:$G$21,2)/(1+$A10)^2+INDEX(Forecast_Model!$C$21:$G$21,3)/(1+$A10)^3+INDEX(Forecast_Model!$C$21:$G$21,4)/(1+$A10)^4+INDEX(Forecast_Model!$C$21:$G$21,5)/(1+$A10)^5+((INDEX(Forecast_Model!$C$21:$G$21,5)*(1+E$5))/($A10-E$5))/(1+$A10)^5)+Raw_Data!$F$23-Raw_Data!$F$31)/Raw_Data!$F$18 -> 139.23475 | F10: =((INDEX(Forecast_Model!$C$21:$G$21,1)/(1+$A10)^1+INDEX(Forecast_Model!$C$21:$G$21,2)/(1+$A10)^2+INDEX(Forecast_Model!$C$21:$G$21,3)/(1+$A10)^3+INDEX(Forecast_Model!$C$21:$G$21,4)/(1+$A10)^4+INDEX(Forecast_Model!$C$21:$G$21,5)/(1+$A10)^5+((INDEX(Forecast_Model!$C$21:$G$21,5)*(1+F$5))/($A10-F$5))/(1+$A10)^5)+Raw_Data!$F$23-Raw_Data!$F$31)/Raw_Data!$F$18 -> 148.6518 | G10: =((INDEX(Forecast_Model!$C$21:$G$21,1)/(1+$A10)^1+INDEX(Forecast_Model!$C$21:$G$21,2)/(1+$A10)^2+INDEX(Forecast_Model!$C$21:$G$21,3)/(1+$A10)^3+INDEX(Forecast_Model!$C$21:$G$21,4)/(1+$A10)^4+INDEX(Forecast_Model!$C$21:$G$21,5)/(1+$A10)^5+((INDEX(Forecast_Model!$C$21:$G$21,5)*(1+G$5))/($A10-G$5))/(1+$A10)^5)+Raw_Data!$F$23-Raw_Data!$F$31)/Raw_Data!$F$18 -> 159.78106
A12: Rows = WACC (7.5% to 9.5% in 0.5% steps); Columns = Terminal Growth Rate g (2.0% to 4.0% in 0.5% steps), matching the ranges specified in the model brief. Each cell independently recomputes: PV of Years 1-5 FCFF (pulled live from Forecast_Model) + PV of Terminal Value (Gordon Growth) at that cell's WACC/g, then bridges to equity value using FY2025 Cash and Total Debt and Diluted Shares from Raw_Data, exactly as in DCF_Valuation. The DCF_Valuation tab's own WACC (~9.5%, from WACC_Calculation) and default g (2.5%) sit near the bottom-right of this grid, for reference.
A14: How to read this table:
A15: - Moving right (higher g) increases the implied share price — a higher terminal growth assumption raises the perpetuity value.
A16: - Moving down (higher WACC) decreases the implied share price — a higher discount rate reduces the present value of future cash flows.
A17: - The (WACC - g) spread in the denominator of the Terminal Value formula means the grid gets increasingly sensitive as WACC approaches g.
